CHANGELOG
LICENSE
MANIFEST.in
README.rst
requirements.txt
setup.py
octogrid/__init__.py
octogrid/octogrid.py
octogrid/settings.py
octogrid.egg-info/PKG-INFO
octogrid.egg-info/SOURCES.txt
octogrid.egg-info/dependency_links.txt
octogrid.egg-info/entry_points.txt
octogrid.egg-info/requires.txt
octogrid.egg-info/top_level.txt
octogrid/auth/__init__.py
octogrid/auth/auth.py
octogrid/builder/__init__.py
octogrid/builder/builder.py
octogrid/generator/__init__.py
octogrid/generator/generator.py
octogrid/parser/__init__.py
octogrid/parser/parser.py
octogrid/publisher/__init__.py
octogrid/publisher/publisher.py
octogrid/store/__init__.py
octogrid/store/store.py
octogrid/utils/__init__.py
octogrid/utils/utils.py