Metadata-Version: 1.1
Name: octogrid
Version: 1.2.0
Summary: GitHub following network visualizer for Humans
Home-page: https://github.com/pravj/octogrid
Author: Pravendra Singh
Author-email: hackpravj@gmail.com
License: MIT
Keywords: github network graph plotly plot chart visualization
Platform: UNKNOWN
Classifier: Development Status :: 5 - Production/Stable
Classifier: Environment :: Console
Classifier: Operating System :: OS Independent
Classifier: Intended Audience :: Developers
Classifier: License :: OSI Approved :: MIT License
Classifier: Natural Language :: English
Classifier: Programming Language :: Python :: 2.6
Classifier: Programming Language :: Python :: 2.7
